hayalib/__init__.py
hayalib-0.0.1.dist-info/METADATA
hayalib-0.0.1.dist-info/WHEEL
hayalib-0.0.1.dist-info/top_level.txt
hayalib-0.0.1.dist-info/RECORD
