Metadata-Version: 2.4
Name: hayalib
Version: 0.0.1
Summary: 哈基密文API库
Author-email: WIFI连接超时 <localaccount@qq.com>
License: GPLv3
Requires-Python: >=3.8
